st_df_table/__init__.py
st_df_table/example.py
st_df_table/frontend/build/asset-manifest.json
st_df_table/frontend/build/index.html
st_df_table/frontend/build/static/css/main.76bce994.css
st_df_table/frontend/build/static/css/main.76bce994.css.map
st_df_table/frontend/build/static/js/main.99f0e205.js
st_df_table/frontend/build/static/js/main.99f0e205.js.LICENSE.txt
st_df_table/frontend/build/static/js/main.99f0e205.js.map
st_df_table-0.0.9.dist-info/LICENSE
st_df_table-0.0.9.dist-info/METADATA
st_df_table-0.0.9.dist-info/WHEEL
st_df_table-0.0.9.dist-info/top_level.txt
st_df_table-0.0.9.dist-info/RECORD
