Metadata-Version: 2.1
Name: st-df-table
Version: 0.0.9
Summary: Alternative to `st.table` with configuration displaying Pandas DataFrame
Home-page: https://github.com/mysiar-org/st-table
Author: Piotr Synowiec
Author-email: psynowiec@gmail.com
License: MIT
Project-URL: Documentation, https://mysiar-org.github.io/st-df-table
Project-URL: Changelog, https://github.com/mysiar-org/st-table/blob/master/CHANGELOG.md
Project-URL: Issues, https://github.com/mysiar-org/st-table/issues
Project-URL: Examples, https://mysiar-org-st-table-st-df.streamlit.app
Keywords: streamlit,streamlit-component
Classifier: Intended Audience :: Developers
Classifier: Programming Language :: Python :: 3 :: Only
Classifier: Topic :: Software Development :: Libraries
Classifier: Topic :: Scientific/Engineering :: Visualization
Classifier: License :: OSI Approved :: MIT License
Requires-Python: >=3.7
License-File: LICENSE
Requires-Dist: streamlit>=0.63
Requires-Dist: pandas
Provides-Extra: devel
Requires-Dist: wheel; extra == "devel"
